pickledir/__init__.py
pickledir/_constants.py
pickledir/_hex.py
pickledir/_pickledir.py
pickledir-0.3.5.dist-info/LICENSE
pickledir-0.3.5.dist-info/METADATA
pickledir-0.3.5.dist-info/WHEEL
pickledir-0.3.5.dist-info/top_level.txt
pickledir-0.3.5.dist-info/RECORD
