Metadata-Version: 2.1
Name: pickledir
Version: 0.3.5
Summary: File-based key-value storage for pickle-serializable keys and values.
Home-page: https://github.com/rtmigo/pickledir_py#readme
Author: Artёm IG
Author-email: ortemeo@gmail.com
License: MIT
Keywords: cache,pickle,file,directory,caching,data,dict
Platform: UNKNOWN
Classifier: Development Status :: 4 - Beta
Classifier: License :: OSI Approved :: MIT License
Classifier: Programming Language :: Python :: 3.8
Classifier: Programming Language :: Python :: 3.9
Classifier: Operating System :: POSIX
Classifier: Operating System :: Microsoft :: Windows
Requires-Python: >=3.8
